outbreak_data/__init__.py
outbreak_data/authenticate_user.py
outbreak_data/outbreak_data.py
outbreak_tools/__init__.py
outbreak_tools/outbreak_tools.py
python_outbreak_info-1.0.4.dist-info/LICENSE.md
python_outbreak_info-1.0.4.dist-info/METADATA
python_outbreak_info-1.0.4.dist-info/WHEEL
python_outbreak_info-1.0.4.dist-info/top_level.txt
python_outbreak_info-1.0.4.dist-info/RECORD
