Metadata-Version: 2.1
Name: python_outbreak_info
Version: 1.0.4
Summary: Python interface to Outbreak.info, powered by GISAID
Home-page: https://github.com/outbreak-info/python-outbreak-info
Author: Outbreak.info dev team
Author-email: lhughes@scripps.edu
License: MIT
License-File: LICENSE.md
Requires-Dist: numpy
Requires-Dist: pandas
Requires-Dist: requests
